mongodb_connect/__init__.py
mongodb_connect/mongo_crud.py
databaseautomation_sunny-0.0.4.dist-info/METADATA
databaseautomation_sunny-0.0.4.dist-info/WHEEL
databaseautomation_sunny-0.0.4.dist-info/top_level.txt
databaseautomation_sunny-0.0.4.dist-info/RECORD
